README.md
setup.py
pro_video_ferramentas/__init__.py
pro_video_ferramentas/camera.py
pro_video_ferramentas/video.py
pro_video_ferramentas.egg-info/PKG-INFO
pro_video_ferramentas.egg-info/SOURCES.txt
pro_video_ferramentas.egg-info/dependency_links.txt
pro_video_ferramentas.egg-info/top_level.txt