Metadata-Version: 1.0
Name: pro-video-ferramentas
Version: 1.0
Summary: Este pacote irá fornecer ferramentas de processamento de vídeo
Home-page: UNKNOWN
Author: Jhonatan
Author-email: jhonatan@gmail.com
License: UNKNOWN
Keywords: camera,video,processamento
Platform: UNKNOWN
